solidityscan_agent/__init__.py
solidityscan_agent/config.py
solidityscan_agent/constants.py
solidityscan_agent/exceptions.py
solidityscan_agent/lang.py
solidityscan_agent/report.py
solidityscan_agent/scan.py
solidityscan-0.2.1.dist-info/METADATA
solidityscan-0.2.1.dist-info/WHEEL
solidityscan-0.2.1.dist-info/entry_points.txt
solidityscan-0.2.1.dist-info/top_level.txt
solidityscan-0.2.1.dist-info/RECORD
