Metadata-Version: 2.1
Name: solidityscan
Version: 0.2.1
Summary: Get your smart contracts audited by a smarter tool
Home-page: https://solidityscan.com
Requires-Python: >=3.6
